.gitignore
LICENSE
README.md
app.py
requirements.txt
setup.cfg
setup.py
api/resource/application-dell-development.yml
api/resource/application-dev.yml
api/resource/application-local.yml
api/resource/application.yml
api/src/QueueManagerApi.py
api/src/client/EmissionClient.py
api/src/client/emitter/MessageEmitter.py
api/src/client/listener/MessageListener.py
api/src/config/MessageConfig.py
api/src/constant/AuditoryConstant.py
api/src/constant/EmissionConstant.py
api/src/controller/MemoryController.py
api/src/controller/MessageController.py
api/src/controller/MessateTestController.py
api/src/controller/QueueModelController.py
api/src/controller/SubscriptionModelController.py
api/src/dto/EmissionDto.py
api/src/enumeration/AccessDomain.py
api/src/helper/EmissionModelHelper.py
api/src/helper/static/EmissionModelHelperStatic.py
api/src/mapper/EmissionModelMapper.py
api/src/mapper/MessageModelMapper.py
api/src/mapper/QueueModelMapper.py
api/src/mapper/SubscriptionModelMapper.py
api/src/memory/mapper/EmissionMapper.py
api/src/memory/mapper/MessageMapper.py
api/src/memory/model/Emission.py
api/src/memory/model/Message.py
api/src/memory/repository/MemoryRepository.py
api/src/memory/service/EmissionService.py
api/src/memory/service/MemoryService.py
api/src/memory/service/MessageService.py
api/src/memory/validator/EmissionValidator.py
api/src/memory/validator/MemoryValidator.py
api/src/memory/validator/MessageValidator.py
api/src/model/EmissionModel.py
api/src/model/MessageModel.py
api/src/model/ModelAssociation.py
api/src/model/QueueModel.py
api/src/model/SubscriptionModel.py
api/src/repository/EmissionModelRepository.py
api/src/repository/MessageModelRepository.py
api/src/repository/QueueModelRepository.py
api/src/repository/SubscriptionModelRepository.py
api/src/scheduler/EmissionScheduler.py
api/src/scheduler/MemoryScheduler.py
api/src/scheduler/MessageScheduler.py
api/src/service/EmissionModelService.py
api/src/service/MessageModelService.py
queue_manager_api.egg-info/PKG-INFO
queue_manager_api.egg-info/SOURCES.txt
queue_manager_api.egg-info/dependency_links.txt
queue_manager_api.egg-info/requires.txt
queue_manager_api.egg-info/top_level.txt
